LICENSE
MANIFEST.in
setup.py
aardtools/__init__.py
aardtools/aard.py
aardtools/compiler.py
aardtools/fetchsiteinfo.py
aardtools/mwaardhtmlwriter.py
aardtools/tex.py
aardtools/wiki.py
aardtools/wordnet.py
aardtools/xdxf.py
aardtools.egg-info/PKG-INFO
aardtools.egg-info/SOURCES.txt
aardtools.egg-info/dependency_links.txt
aardtools.egg-info/entry_points.txt
aardtools.egg-info/requires.txt
aardtools.egg-info/top_level.txt
doc/aardformat.rst
doc/aardtools.rst
test/test_temp_article_store.py
test/test_xdxf.py
wiki/en/copyright.txt
wiki/en/license.txt
wiki/en/metadata.ini