Metadata-Version: 1.0
Name: aardtools
Version: 0.8.3
Summary: Tools to create dictionaries in aarddict format.
Home-page: http://aarddict.org
Author: Igor Tkach
Author-email: itkach@aarddict.org
License: GPL 3
Keywords: aarddict,aardtools,wiki,wikipedia,xdxf,dict,dictionary,maemo
Platform: UNKNOWN
Classifier: Development Status :: 3 - Alpha
Classifier: Operating System :: OS Independent
Classifier: Programming Language :: Python
Classifier: License :: OSI Approved :: GNU General Public License (GPL)
Classifier: Topic :: Utilities
Classifier: Environment :: Console
